[
  {
    "ContainingType": "BackEnd.Controllers.AlbumController",
    "Method": "Post",
    "RelativePath": "api/Album/album",
    "HttpMethod": "POST",
    "IsController": true,
    "Order": 0,
    "Parameters": [
      {
        "Name": "createAlbumDto",
        "Type": "BackEnd.Models.Dtos.CreateAlbumDto",
        "IsRequired": true
      }
    ],
    "ReturnTypes": [
      {
        "Type": "BackEnd.Models.Dtos.AlbumDto",
        "MediaTypes": [
          "text/plain",
          "application/json",
          "text/json"
        ],
        "StatusCode": 200
      }
    ]
  },
  {
    "ContainingType": "BackEnd.Controllers.AlbumController",
    "Method": "GetById",
    "RelativePath": "api/Album/albumbyid/{id}",
    "HttpMethod": "GET",
    "IsController": true,
    "Order": 0,
    "Parameters": [
      {
        "Name": "id",
        "Type": "System.Guid",
        "IsRequired": true
      }
    ],
    "ReturnTypes": [
      {
        "Type": "BackEnd.Models.Album",
        "MediaTypes": [
          "text/plain",
          "application/json",
          "text/json"
        ],
        "StatusCode": 200
      }
    ]
  },
  {
    "ContainingType": "BackEnd.Controllers.AlbumController",
    "Method": "Get",
    "RelativePath": "api/Album/allalbum",
    "HttpMethod": "GET",
    "IsController": true,
    "Order": 0,
    "Parameters": [],
    "ReturnTypes": [
      {
        "Type": "System.Collections.Generic.IEnumerable\u00601[[BackEnd.Models.Album, BackEnd, Version=1.0.0.0, Culture=neutral, PublicKeyToken=null]]",
        "MediaTypes": [
          "text/plain",
          "application/json",
          "text/json"
        ],
        "StatusCode": 200
      }
    ]
  },
  {
    "ContainingType": "BackEnd.Controllers.AlbumController",
    "Method": "DeleteById",
    "RelativePath": "api/Album/deletebyid/{id}",
    "HttpMethod": "DELETE",
    "IsController": true,
    "Order": 0,
    "Parameters": [
      {
        "Name": "id",
        "Type": "System.Guid",
        "IsRequired": true
      }
    ],
    "ReturnTypes": [
      {
        "Type": "BackEnd.Models.Album",
        "MediaTypes": [
          "text/plain",
          "application/json",
          "text/json"
        ],
        "StatusCode": 200
      }
    ]
  },
  {
    "ContainingType": "BackEnd.Controllers.AlbumController",
    "Method": "Put",
    "RelativePath": "api/Album/updatebyid/{id}",
    "HttpMethod": "PUT",
    "IsController": true,
    "Order": 0,
    "Parameters": [
      {
        "Name": "id",
        "Type": "System.Guid",
        "IsRequired": true
      },
      {
        "Name": "modifyAlbumDto",
        "Type": "BackEnd.Models.Dtos.ModifyAlbumDto",
        "IsRequired": true
      }
    ],
    "ReturnTypes": [
      {
        "Type": "BackEnd.Models.Album",
        "MediaTypes": [
          "text/plain",
          "application/json",
          "text/json"
        ],
        "StatusCode": 200
      }
    ]
  },
  {
    "ContainingType": "BackEnd.Controllers.ArtistController",
    "Method": "Get",
    "RelativePath": "api/Artist/allartist",
    "HttpMethod": "GET",
    "IsController": true,
    "Order": 0,
    "Parameters": [],
    "ReturnTypes": [
      {
        "Type": "System.Collections.Generic.IEnumerable\u00601[[BackEnd.Models.Artist, BackEnd, Version=1.0.0.0, Culture=neutral, PublicKeyToken=null]]",
        "MediaTypes": [
          "text/plain",
          "application/json",
          "text/json"
        ],
        "StatusCode": 200
      }
    ]
  },
  {
    "ContainingType": "BackEnd.Controllers.ArtistController",
    "Method": "Post",
    "RelativePath": "api/Artist/artist",
    "HttpMethod": "POST",
    "IsController": true,
    "Order": 0,
    "Parameters": [
      {
        "Name": "createArtistDto",
        "Type": "BackEnd.Models.Dtos.CreateArtistDto",
        "IsRequired": true
      }
    ],
    "ReturnTypes": [
      {
        "Type": "BackEnd.Models.Dtos.ArtistDto",
        "MediaTypes": [
          "text/plain",
          "application/json",
          "text/json"
        ],
        "StatusCode": 200
      }
    ]
  },
  {
    "ContainingType": "BackEnd.Controllers.ArtistController",
    "Method": "GetById",
    "RelativePath": "api/Artist/artistbyid/{id}",
    "HttpMethod": "GET",
    "IsController": true,
    "Order": 0,
    "Parameters": [
      {
        "Name": "id",
        "Type": "System.Guid",
        "IsRequired": true
      }
    ],
    "ReturnTypes": [
      {
        "Type": "BackEnd.Models.Artist",
        "MediaTypes": [
          "text/plain",
          "application/json",
          "text/json"
        ],
        "StatusCode": 200
      }
    ]
  },
  {
    "ContainingType": "BackEnd.Controllers.ArtistController",
    "Method": "DeleteById",
    "RelativePath": "api/Artist/deletebyid/{id}",
    "HttpMethod": "DELETE",
    "IsController": true,
    "Order": 0,
    "Parameters": [
      {
        "Name": "id",
        "Type": "System.Guid",
        "IsRequired": true
      }
    ],
    "ReturnTypes": [
      {
        "Type": "BackEnd.Models.Artist",
        "MediaTypes": [
          "text/plain",
          "application/json",
          "text/json"
        ],
        "StatusCode": 200
      }
    ]
  },
  {
    "ContainingType": "BackEnd.Controllers.ArtistController",
    "Method": "Put",
    "RelativePath": "api/Artist/updatebyid/{id}",
    "HttpMethod": "PUT",
    "IsController": true,
    "Order": 0,
    "Parameters": [
      {
        "Name": "id",
        "Type": "System.Guid",
        "IsRequired": true
      },
      {
        "Name": "modifyArtistDto",
        "Type": "BackEnd.Models.Dtos.ModifyArtistDto",
        "IsRequired": true
      }
    ],
    "ReturnTypes": [
      {
        "Type": "BackEnd.Models.Artist",
        "MediaTypes": [
          "text/plain",
          "application/json",
          "text/json"
        ],
        "StatusCode": 200
      }
    ]
  },
  {
    "ContainingType": "BackEnd.Controllers.ArtistSongController",
    "Method": "Get",
    "RelativePath": "api/ArtistSong/allartistsong",
    "HttpMethod": "GET",
    "IsController": true,
    "Order": 0,
    "Parameters": [],
    "ReturnTypes": [
      {
        "Type": "System.Collections.Generic.IEnumerable\u00601[[BackEnd.Models.ArtistSong, BackEnd, Version=1.0.0.0, Culture=neutral, PublicKeyToken=null]]",
        "MediaTypes": [
          "text/plain",
          "application/json",
          "text/json"
        ],
        "StatusCode": 200
      }
    ]
  },
  {
    "ContainingType": "BackEnd.Controllers.ArtistSongController",
    "Method": "Post",
    "RelativePath": "api/ArtistSong/artistsong",
    "HttpMethod": "POST",
    "IsController": true,
    "Order": 0,
    "Parameters": [
      {
        "Name": "createArtistSongDto",
        "Type": "BackEnd.Models.Dtos.CreateArtistSongDto",
        "IsRequired": true
      }
    ],
    "ReturnTypes": [
      {
        "Type": "BackEnd.Models.Dtos.ArtistSongDto",
        "MediaTypes": [
          "text/plain",
          "application/json",
          "text/json"
        ],
        "StatusCode": 200
      }
    ]
  },
  {
    "ContainingType": "BackEnd.Controllers.ArtistSongController",
    "Method": "GetById",
    "RelativePath": "api/ArtistSong/artistsongbyid/{artistid, songid}",
    "HttpMethod": "GET",
    "IsController": true,
    "Order": 0,
    "Parameters": [
      {
        "Name": "artistid",
        "Type": "System.Guid",
        "IsRequired": false
      },
      {
        "Name": "songid",
        "Type": "System.Guid",
        "IsRequired": false
      },
      {
        "Name": "artistid, songid",
        "Type": "",
        "IsRequired": true
      }
    ],
    "ReturnTypes": [
      {
        "Type": "BackEnd.Models.ArtistSong",
        "MediaTypes": [
          "text/plain",
          "application/json",
          "text/json"
        ],
        "StatusCode": 200
      }
    ]
  },
  {
    "ContainingType": "BackEnd.Controllers.ArtistSongController",
    "Method": "DeleteById",
    "RelativePath": "api/ArtistSong/deletebyid/{artistid, songid}",
    "HttpMethod": "DELETE",
    "IsController": true,
    "Order": 0,
    "Parameters": [
      {
        "Name": "artistid",
        "Type": "System.Guid",
        "IsRequired": false
      },
      {
        "Name": "songid",
        "Type": "System.Guid",
        "IsRequired": false
      },
      {
        "Name": "artistid, songid",
        "Type": "",
        "IsRequired": true
      }
    ],
    "ReturnTypes": [
      {
        "Type": "BackEnd.Models.ArtistSong",
        "MediaTypes": [
          "text/plain",
          "application/json",
          "text/json"
        ],
        "StatusCode": 200
      }
    ]
  },
  {
    "ContainingType": "BackEnd.Controllers.ArtistSongController",
    "Method": "Put",
    "RelativePath": "api/ArtistSong/updatebyid/{artistid}/{songid}",
    "HttpMethod": "PUT",
    "IsController": true,
    "Order": 0,
    "Parameters": [
      {
        "Name": "artistid",
        "Type": "System.Guid",
        "IsRequired": true
      },
      {
        "Name": "songid",
        "Type": "System.Guid",
        "IsRequired": true
      },
      {
        "Name": "modifyArtistSongDto",
        "Type": "BackEnd.Models.Dtos.ModifyArtistSongDto",
        "IsRequired": true
      }
    ],
    "ReturnTypes": [
      {
        "Type": "BackEnd.Models.ArtistSong",
        "MediaTypes": [
          "text/plain",
          "application/json",
          "text/json"
        ],
        "StatusCode": 200
      }
    ]
  },
  {
    "ContainingType": "BackEnd.Controllers.ConnectionController",
    "Method": "GetAllPlaylistDetails",
    "RelativePath": "api/Connection/allplaylistdetails",
    "HttpMethod": "GET",
    "IsController": true,
    "Order": 0,
    "Parameters": [],
    "ReturnTypes": [
      {
        "Type": "System.Collections.Generic.IEnumerable\u00601[[System.Object, System.Private.CoreLib, Version=8.0.0.0, Culture=neutral, PublicKeyToken=7cec85d7bea7798e]]",
        "MediaTypes": [
          "text/plain",
          "application/json",
          "text/json"
        ],
        "StatusCode": 200
      }
    ]
  },
  {
    "ContainingType": "BackEnd.Controllers.ConnectionController",
    "Method": "GetAllSongDetails",
    "RelativePath": "api/Connection/allsongdetails",
    "HttpMethod": "GET",
    "IsController": true,
    "Order": 0,
    "Parameters": [],
    "ReturnTypes": [
      {
        "Type": "System.Collections.Generic.IEnumerable\u00601[[System.Object, System.Private.CoreLib, Version=8.0.0.0, Culture=neutral, PublicKeyToken=7cec85d7bea7798e]]",
        "MediaTypes": [
          "text/plain",
          "application/json",
          "text/json"
        ],
        "StatusCode": 200
      }
    ]
  },
  {
    "ContainingType": "BackEnd.Controllers.ConnectionController",
    "Method": "GetPlaylistDetailsById",
    "RelativePath": "api/Connection/playlistdetailsby/{id}",
    "HttpMethod": "GET",
    "IsController": true,
    "Order": 0,
    "Parameters": [
      {
        "Name": "id",
        "Type": "System.Guid",
        "IsRequired": true
      }
    ],
    "ReturnTypes": []
  },
  {
    "ContainingType": "BackEnd.Controllers.ConnectionController",
    "Method": "GetSongDetailsById",
    "RelativePath": "api/Connection/songdetails/{id}",
    "HttpMethod": "GET",
    "IsController": true,
    "Order": 0,
    "Parameters": [
      {
        "Name": "id",
        "Type": "System.Guid",
        "IsRequired": true
      }
    ],
    "ReturnTypes": []
  },
  {
    "ContainingType": "MetadataController",
    "Method": "GetMetadata",
    "RelativePath": "api/Metadata",
    "HttpMethod": "GET",
    "IsController": true,
    "Order": 0,
    "Parameters": [],
    "ReturnTypes": []
  },
  {
    "ContainingType": "BackEnd.Controllers.PlaylistController",
    "Method": "Get",
    "RelativePath": "api/Playlist/allplaylist",
    "HttpMethod": "GET",
    "IsController": true,
    "Order": 0,
    "Parameters": [],
    "ReturnTypes": [
      {
        "Type": "System.Collections.Generic.IEnumerable\u00601[[BackEnd.Models.Playlist, BackEnd, Version=1.0.0.0, Culture=neutral, PublicKeyToken=null]]",
        "MediaTypes": [
          "text/plain",
          "application/json",
          "text/json"
        ],
        "StatusCode": 200
      }
    ]
  },
  {
    "ContainingType": "BackEnd.Controllers.PlaylistController",
    "Method": "DeleteById",
    "RelativePath": "api/Playlist/deletebyid/{id}",
    "HttpMethod": "DELETE",
    "IsController": true,
    "Order": 0,
    "Parameters": [
      {
        "Name": "id",
        "Type": "System.Guid",
        "IsRequired": true
      }
    ],
    "ReturnTypes": [
      {
        "Type": "BackEnd.Models.Playlist",
        "MediaTypes": [
          "text/plain",
          "application/json",
          "text/json"
        ],
        "StatusCode": 200
      }
    ]
  },
  {
    "ContainingType": "BackEnd.Controllers.PlaylistController",
    "Method": "Post",
    "RelativePath": "api/Playlist/playlist",
    "HttpMethod": "POST",
    "IsController": true,
    "Order": 0,
    "Parameters": [
      {
        "Name": "createPlaylistDto",
        "Type": "BackEnd.Models.Dtos.CreatePlaylistDto",
        "IsRequired": true
      }
    ],
    "ReturnTypes": [
      {
        "Type": "BackEnd.Models.Dtos.PlaylistDto",
        "MediaTypes": [
          "text/plain",
          "application/json",
          "text/json"
        ],
        "StatusCode": 200
      }
    ]
  },
  {
    "ContainingType": "BackEnd.Controllers.PlaylistController",
    "Method": "GetById",
    "RelativePath": "api/Playlist/playlistbyid/{id}",
    "HttpMethod": "GET",
    "IsController": true,
    "Order": 0,
    "Parameters": [
      {
        "Name": "id",
        "Type": "System.Guid",
        "IsRequired": true
      }
    ],
    "ReturnTypes": [
      {
        "Type": "BackEnd.Models.Playlist",
        "MediaTypes": [
          "text/plain",
          "application/json",
          "text/json"
        ],
        "StatusCode": 200
      }
    ]
  },
  {
    "ContainingType": "BackEnd.Controllers.PlaylistController",
    "Method": "Put",
    "RelativePath": "api/Playlist/updatebyid/{id}",
    "HttpMethod": "PUT",
    "IsController": true,
    "Order": 0,
    "Parameters": [
      {
        "Name": "id",
        "Type": "System.Guid",
        "IsRequired": true
      },
      {
        "Name": "modifyPlaylistDto",
        "Type": "BackEnd.Models.Dtos.ModifyPlaylistDto",
        "IsRequired": true
      }
    ],
    "ReturnTypes": [
      {
        "Type": "BackEnd.Models.Playlist",
        "MediaTypes": [
          "text/plain",
          "application/json",
          "text/json"
        ],
        "StatusCode": 200
      }
    ]
  },
  {
    "ContainingType": "BackEnd.Controllers.PlaylistsongController",
    "Method": "Get",
    "RelativePath": "api/Playlistsong/allplaylistsong",
    "HttpMethod": "GET",
    "IsController": true,
    "Order": 0,
    "Parameters": [],
    "ReturnTypes": [
      {
        "Type": "System.Collections.Generic.IEnumerable\u00601[[BackEnd.Models.PlaylistSong, BackEnd, Version=1.0.0.0, Culture=neutral, PublicKeyToken=null]]",
        "MediaTypes": [
          "text/plain",
          "application/json",
          "text/json"
        ],
        "StatusCode": 200
      }
    ]
  },
  {
    "ContainingType": "BackEnd.Controllers.PlaylistsongController",
    "Method": "DeleteById",
    "RelativePath": "api/Playlistsong/deletebyid/{playlistid, songid}",
    "HttpMethod": "DELETE",
    "IsController": true,
    "Order": 0,
    "Parameters": [
      {
        "Name": "playlistid",
        "Type": "System.Guid",
        "IsRequired": false
      },
      {
        "Name": "songid",
        "Type": "System.Guid",
        "IsRequired": false
      },
      {
        "Name": "playlistid, songid",
        "Type": "",
        "IsRequired": true
      }
    ],
    "ReturnTypes": [
      {
        "Type": "BackEnd.Models.PlaylistSong",
        "MediaTypes": [
          "text/plain",
          "application/json",
          "text/json"
        ],
        "StatusCode": 200
      }
    ]
  },
  {
    "ContainingType": "BackEnd.Controllers.PlaylistsongController",
    "Method": "Post",
    "RelativePath": "api/Playlistsong/playlistsong",
    "HttpMethod": "POST",
    "IsController": true,
    "Order": 0,
    "Parameters": [
      {
        "Name": "createPlaylistsongDto",
        "Type": "BackEnd.Models.Dtos.CreatePlaylistSongDto",
        "IsRequired": true
      }
    ],
    "ReturnTypes": [
      {
        "Type": "BackEnd.Models.Dtos.PlaylistSongDto",
        "MediaTypes": [
          "text/plain",
          "application/json",
          "text/json"
        ],
        "StatusCode": 200
      }
    ]
  },
  {
    "ContainingType": "BackEnd.Controllers.PlaylistsongController",
    "Method": "GetById",
    "RelativePath": "api/Playlistsong/playlistsongbyid/{playlistid, songid}",
    "HttpMethod": "GET",
    "IsController": true,
    "Order": 0,
    "Parameters": [
      {
        "Name": "playlistid",
        "Type": "System.Guid",
        "IsRequired": false
      },
      {
        "Name": "songid",
        "Type": "System.Guid",
        "IsRequired": false
      },
      {
        "Name": "playlistid, songid",
        "Type": "",
        "IsRequired": true
      }
    ],
    "ReturnTypes": [
      {
        "Type": "BackEnd.Models.PlaylistSong",
        "MediaTypes": [
          "text/plain",
          "application/json",
          "text/json"
        ],
        "StatusCode": 200
      }
    ]
  },
  {
    "ContainingType": "BackEnd.Controllers.PlaylistsongController",
    "Method": "Put",
    "RelativePath": "api/Playlistsong/updatebyid/{playlistid}/{songid}",
    "HttpMethod": "PUT",
    "IsController": true,
    "Order": 0,
    "Parameters": [
      {
        "Name": "playlistid",
        "Type": "System.Guid",
        "IsRequired": true
      },
      {
        "Name": "songid",
        "Type": "System.Guid",
        "IsRequired": true
      },
      {
        "Name": "modifyPlaylistSongDto",
        "Type": "BackEnd.Models.Dtos.ModifyPlaylistSongDto",
        "IsRequired": true
      }
    ],
    "ReturnTypes": [
      {
        "Type": "BackEnd.Models.PlaylistSong",
        "MediaTypes": [
          "text/plain",
          "application/json",
          "text/json"
        ],
        "StatusCode": 200
      }
    ]
  },
  {
    "ContainingType": "BackEnd.Controllers.SongController",
    "Method": "Get",
    "RelativePath": "api/Song/allsong",
    "HttpMethod": "GET",
    "IsController": true,
    "Order": 0,
    "Parameters": [],
    "ReturnTypes": [
      {
        "Type": "System.Collections.Generic.IEnumerable\u00601[[BackEnd.Models.Song, BackEnd, Version=1.0.0.0, Culture=neutral, PublicKeyToken=null]]",
        "MediaTypes": [
          "text/plain",
          "application/json",
          "text/json"
        ],
        "StatusCode": 200
      }
    ]
  },
  {
    "ContainingType": "BackEnd.Controllers.SongController",
    "Method": "DeleteById",
    "RelativePath": "api/Song/deletebyid/{id}",
    "HttpMethod": "DELETE",
    "IsController": true,
    "Order": 0,
    "Parameters": [
      {
        "Name": "id",
        "Type": "System.Guid",
        "IsRequired": true
      }
    ],
    "ReturnTypes": [
      {
        "Type": "BackEnd.Models.Song",
        "MediaTypes": [
          "text/plain",
          "application/json",
          "text/json"
        ],
        "StatusCode": 200
      }
    ]
  },
  {
    "ContainingType": "BackEnd.Controllers.SongController",
    "Method": "Post",
    "RelativePath": "api/Song/song",
    "HttpMethod": "POST",
    "IsController": true,
    "Order": 0,
    "Parameters": [
      {
        "Name": "createSongDto",
        "Type": "BackEnd.Models.Dtos.CreateSongDto",
        "IsRequired": true
      }
    ],
    "ReturnTypes": [
      {
        "Type": "BackEnd.Models.Dtos.SongDto",
        "MediaTypes": [
          "text/plain",
          "application/json",
          "text/json"
        ],
        "StatusCode": 200
      }
    ]
  },
  {
    "ContainingType": "BackEnd.Controllers.SongController",
    "Method": "GetById",
    "RelativePath": "api/Song/songbyid/{id}",
    "HttpMethod": "GET",
    "IsController": true,
    "Order": 0,
    "Parameters": [
      {
        "Name": "id",
        "Type": "System.Guid",
        "IsRequired": true
      }
    ],
    "ReturnTypes": [
      {
        "Type": "BackEnd.Models.Song",
        "MediaTypes": [
          "text/plain",
          "application/json",
          "text/json"
        ],
        "StatusCode": 200
      }
    ]
  },
  {
    "ContainingType": "BackEnd.Controllers.SongController",
    "Method": "Put",
    "RelativePath": "api/Song/updatebyid/{id}",
    "HttpMethod": "PUT",
    "IsController": true,
    "Order": 0,
    "Parameters": [
      {
        "Name": "id",
        "Type": "System.Guid",
        "IsRequired": true
      },
      {
        "Name": "modifySongDto",
        "Type": "BackEnd.Models.Dtos.ModifySongDto",
        "IsRequired": true
      }
    ],
    "ReturnTypes": [
      {
        "Type": "BackEnd.Models.Song",
        "MediaTypes": [
          "text/plain",
          "application/json",
          "text/json"
        ],
        "StatusCode": 200
      }
    ]
  },
  {
    "ContainingType": "BackEnd.Controllers.UserController",
    "Method": "Get",
    "RelativePath": "api/User/alluser",
    "HttpMethod": "GET",
    "IsController": true,
    "Order": 0,
    "Parameters": [],
    "ReturnTypes": [
      {
        "Type": "System.Collections.Generic.IEnumerable\u00601[[BackEnd.Models.User, BackEnd, Version=1.0.0.0, Culture=neutral, PublicKeyToken=null]]",
        "MediaTypes": [
          "text/plain",
          "application/json",
          "text/json"
        ],
        "StatusCode": 200
      }
    ]
  },
  {
    "ContainingType": "BackEnd.Controllers.UserController",
    "Method": "DeleteById",
    "RelativePath": "api/User/deletebyid/{id}",
    "HttpMethod": "DELETE",
    "IsController": true,
    "Order": 0,
    "Parameters": [
      {
        "Name": "id",
        "Type": "System.Guid",
        "IsRequired": true
      }
    ],
    "ReturnTypes": [
      {
        "Type": "BackEnd.Models.User",
        "MediaTypes": [
          "text/plain",
          "application/json",
          "text/json"
        ],
        "StatusCode": 200
      }
    ]
  },
  {
    "ContainingType": "BackEnd.Controllers.UserController",
    "Method": "Put",
    "RelativePath": "api/User/updatebyid/{id}",
    "HttpMethod": "PUT",
    "IsController": true,
    "Order": 0,
    "Parameters": [
      {
        "Name": "id",
        "Type": "System.Guid",
        "IsRequired": true
      },
      {
        "Name": "modifyUserDto",
        "Type": "BackEnd.Models.Dtos.ModifyUserDto",
        "IsRequired": true
      }
    ],
    "ReturnTypes": [
      {
        "Type": "BackEnd.Models.User",
        "MediaTypes": [
          "text/plain",
          "application/json",
          "text/json"
        ],
        "StatusCode": 200
      }
    ]
  },
  {
    "ContainingType": "BackEnd.Controllers.UserController",
    "Method": "Post",
    "RelativePath": "api/User/user",
    "HttpMethod": "POST",
    "IsController": true,
    "Order": 0,
    "Parameters": [
      {
        "Name": "createUserDto",
        "Type": "BackEnd.Models.Dtos.CreateUserDto",
        "IsRequired": true
      }
    ],
    "ReturnTypes": [
      {
        "Type": "BackEnd.Models.Dtos.UserDto",
        "MediaTypes": [
          "text/plain",
          "application/json",
          "text/json"
        ],
        "StatusCode": 200
      }
    ]
  },
  {
    "ContainingType": "BackEnd.Controllers.UserController",
    "Method": "GetById",
    "RelativePath": "api/User/userbyid/{id}",
    "HttpMethod": "GET",
    "IsController": true,
    "Order": 0,
    "Parameters": [
      {
        "Name": "id",
        "Type": "System.Guid",
        "IsRequired": true
      }
    ],
    "ReturnTypes": [
      {
        "Type": "BackEnd.Models.User",
        "MediaTypes": [
          "text/plain",
          "application/json",
          "text/json"
        ],
        "StatusCode": 200
      }
    ]
  },
  {
    "ContainingType": "SpotifyDownloadController",
    "Method": "Download",
    "RelativePath": "download",
    "HttpMethod": "POST",
    "IsController": true,
    "Order": 0,
    "Parameters": [
      {
        "Name": "request",
        "Type": "Email_Test_API.Models.SpotifyDownloadRequest",
        "IsRequired": true
      }
    ],
    "ReturnTypes": []
  },
  {
    "ContainingType": "SpotifyWebDownloadController",
    "Method": "Download",
    "RelativePath": "downloadweb",
    "HttpMethod": "POST",
    "IsController": true,
    "Order": 0,
    "Parameters": [],
    "ReturnTypes": []
  },
  {
    "ContainingType": "Email_Test_API.Controllers.EmailController",
    "Method": "SendEmail",
    "RelativePath": "email",
    "HttpMethod": "POST",
    "IsController": true,
    "Order": 0,
    "Parameters": [
      {
        "Name": "request",
        "Type": "Email_Test_API.Models.Dtos.EmailDto",
        "IsRequired": true
      }
    ],
    "ReturnTypes": []
  }
]